songdkl/__about__.py
songdkl/__init__.py
songdkl/__main__.py
songdkl/audio.py
songdkl/constants.py
songdkl/load.py
songdkl/logging.py
songdkl/numsyls.py
songdkl/prep.py
songdkl/songdkl.py
songdkl/syllables.py
songdkl/timenow.py
songdkl/argparser/__init__.py
songdkl/argparser/argparser.py
songdkl/argparser/epilogs.py
songdkl-0.4.0.dist-info/entry_points.txt
songdkl-0.4.0.dist-info/LICENSE
songdkl-0.4.0.dist-info/WHEEL
songdkl-0.4.0.dist-info/METADATA
songdkl-0.4.0.dist-info/RECORD
