Metadata-Version: 2.1
Name: songdkl
Version: 0.4.0
Summary: automated quantitation of vocal learning in songbirds
Author: David Mets
Author-email: David Nicholson <nickledave@users.noreply.github.com>
Requires-Python: >=3.8
Classifier: License :: OSI Approved :: BSD License
Classifier: Development Status :: 4 - Beta
Classifier: Programming Language :: Python
Classifier: Programming Language :: Python :: 3
Classifier: Programming Language :: Python :: 3.8
Classifier: Programming Language :: Python :: 3.9
Classifier: Programming Language :: Python :: 3.10
Classifier: Programming Language :: Python :: Implementation :: CPython
Requires-Dist: crowsetta >=4.0.0.post2
Requires-Dist: dask >=2022.12.0
Requires-Dist: numpy >=1.19.4
Requires-Dist: scipy >=1.5.4
Requires-Dist: matplotlib >= 3.3.3
Requires-Dist: rich >=12.5.1
Requires-Dist: scikit-image >= 0.19.3
Requires-Dist: scikit-learn >= 0.24.0
Requires-Dist: zarr >=2.13.3
Requires-Dist: flit ; extra == "dev"
Requires-Dist: twine ; extra == "dev"
Requires-Dist: songdkl[tests, docs] ; extra == "dev"
Requires-Dist: jupyterlab >=3.0.3 ; extra == "docs"
Requires-Dist: Sphinx >= 3.4.1 ; extra == "docs"
Requires-Dist: pandas >= 1.4.4 ; extra == "tests"
Requires-Dist: pytest >= 6.2.1 ; extra == "tests"
Requires-Dist: pytest-cov >=2.12.0 ; extra == "tests"
Requires-Dist: pytest-console-scripts >= 1.3.1 ; extra == "tests"
Project-URL: Home, https://github.com/NickleDave/songdkl
Provides-Extra: dev
Provides-Extra: docs
Provides-Extra: tests
